{
  "package": "org.bukkit.entity",
  "methods": [
    {
      "name": "getClass",
      "return": "java.lang.Class"
    },
    {"name": "notify"},
    {"name": "notifyAll"},
    {"name": "wait"},
    {
      "name": "wait",
      "parameters": [{
        "name": "arg0",
        "type": "long"
      }]
    },
    {
      "name": "wait",
      "parameters": [
        {
          "name": "arg0",
          "type": "long"
        },
        {
          "name": "arg1",
          "type": "int"
        }
      ]
    },
    {
      "name": "name",
      "return": "java.lang.String"
    },
    {
      "name": "ordinal",
      "return": "int"
    },
    {
      "name": "toString",
      "return": "java.lang.String"
    },
    {
      "name": "equals",
      "parameters": [{
        "name": "arg0",
        "type": "java.lang.Object"
      }],
      "return": "boolean"
    },
    {
      "name": "hashCode",
      "return": "int"
    },
    {
      "name": "compareTo",
      "parameters": [{
        "name": "arg0",
        "type": "java.lang.Enum"
      }],
      "return": "int"
    },
    {
      "name": "getDeclaringClass",
      "return": "java.lang.Class"
    },
    {
      "name": "describeConstable",
      "return": "java.util.Optional"
    },
    {
      "static": true,
      "name": "valueOf",
      "parameters": [
        {
          "name": "arg0",
          "type": "java.lang.Class"
        },
        {
          "name": "arg1",
          "type": "java.lang.String"
        }
      ],
      "return": "java.lang.Enum"
    },
    {
      "static": true,
      "name": "values",
      "return": "org.bukkit.entity.ExperienceOrb.SpawnReason[]"
    },
    {
      "static": true,
      "name": "valueOf",
      "parameters": [{
        "name": "name",
        "type": "java.lang.String"
      }],
      "return": "org.bukkit.entity.ExperienceOrb.SpawnReason"
    }
  ],
  "name": "org.bukkit.entity.ExperienceOrb.SpawnReason",
  "simple-name": "SpawnReason",
  "fields": [
    {
      "static": true,
      "name": "PLAYER_DEATH",
      "type": "org.bukkit.entity.ExperienceOrb.SpawnReason"
    },
    {
      "static": true,
      "name": "ENTITY_DEATH",
      "type": "org.bukkit.entity.ExperienceOrb.SpawnReason"
    },
    {
      "static": true,
      "name": "FURNACE",
      "type": "org.bukkit.entity.ExperienceOrb.SpawnReason"
    },
    {
      "static": true,
      "name": "BREED",
      "type": "org.bukkit.entity.ExperienceOrb.SpawnReason"
    },
    {
      "static": true,
      "name": "VILLAGER_TRADE",
      "type": "org.bukkit.entity.ExperienceOrb.SpawnReason"
    },
    {
      "static": true,
      "name": "FISHING",
      "type": "org.bukkit.entity.ExperienceOrb.SpawnReason"
    },
    {
      "static": true,
      "name": "BLOCK_BREAK",
      "type": "org.bukkit.entity.ExperienceOrb.SpawnReason"
    },
    {
      "static": true,
      "name": "CUSTOM",
      "type": "org.bukkit.entity.ExperienceOrb.SpawnReason"
    },
    {
      "static": true,
      "name": "EXP_BOTTLE",
      "type": "org.bukkit.entity.ExperienceOrb.SpawnReason"
    },
    {
      "static": true,
      "name": "GRINDSTONE",
      "type": "org.bukkit.entity.ExperienceOrb.SpawnReason"
    },
    {
      "static": true,
      "name": "UNKNOWN",
      "type": "org.bukkit.entity.ExperienceOrb.SpawnReason"
    }
  ]
}