{
  "constructors": [
    {
      "name": "<init>",
      "parameters": [
        {
          "name": "namespace",
          "type": "java.lang.String"
        },
        {
          "name": "key",
          "type": "java.lang.String"
        }
      ]
    },
    {
      "name": "<init>",
      "parameters": [
        {
          "name": "plugin",
          "type": "org.bukkit.plugin.Plugin"
        },
        {
          "name": "key",
          "type": "java.lang.String"
        }
      ]
    }
  ],
  "package": "org.bukkit",
  "methods": [
    {
      "name": "getClass",
      "return": "java.lang.Class"
    },
    {"name": "notify"},
    {"name": "notifyAll"},
    {"name": "wait"},
    {
      "name": "wait",
      "parameters": [{
        "name": "arg0",
        "type": "long"
      }]
    },
    {
      "name": "wait",
      "parameters": [
        {
          "name": "arg0",
          "type": "long"
        },
        {
          "name": "arg1",
          "type": "int"
        }
      ]
    },
    {
      "name": "getNamespace",
      "return": "java.lang.String"
    },
    {
      "name": "getKey",
      "return": "java.lang.String"
    },
    {
      "name": "hashCode",
      "return": "int"
    },
    {
      "name": "equals",
      "parameters": [{
        "name": "obj",
        "type": "java.lang.Object"
      }],
      "return": "boolean"
    },
    {
      "name": "toString",
      "return": "java.lang.String"
    },
    {
      "static": true,
      "name": "randomKey",
      "return": "org.bukkit.NamespacedKey"
    },
    {
      "static": true,
      "name": "minecraft",
      "parameters": [{
        "name": "key",
        "type": "java.lang.String"
      }],
      "return": "org.bukkit.NamespacedKey"
    },
    {
      "static": true,
      "name": "fromString",
      "parameters": [
        {
          "name": "string",
          "type": "java.lang.String"
        },
        {
          "name": "defaultNamespace",
          "type": "org.bukkit.plugin.Plugin"
        }
      ],
      "return": "org.bukkit.NamespacedKey"
    },
    {
      "static": true,
      "name": "fromString",
      "parameters": [{
        "name": "key",
        "type": "java.lang.String"
      }],
      "return": "org.bukkit.NamespacedKey"
    },
    {
      "name": "namespace",
      "return": "java.lang.String"
    },
    {
      "name": "value",
      "return": "java.lang.String"
    },
    {
      "name": "asString",
      "return": "java.lang.String"
    }
  ],
  "name": "org.bukkit.NamespacedKey",
  "simple-name": "NamespacedKey",
  "fields": [
    {
      "static": true,
      "name": "MINECRAFT",
      "type": "java.lang.String"
    },
    {
      "static": true,
      "name": "BUKKIT",
      "type": "java.lang.String"
    }
  ]
}