{
  "package": "java.util.spi",
  "methods": [
    {
      "name": "getClass",
      "return": "java.lang.Class"
    },
    {
      "name": "hashCode",
      "return": "int"
    },
    {
      "name": "equals",
      "parameters": [{
        "name": "obj",
        "type": "java.lang.Object"
      }],
      "return": "boolean"
    },
    {
      "name": "toString",
      "return": "java.lang.String"
    },
    {"name": "notify"},
    {"name": "notifyAll"},
    {"name": "wait"},
    {
      "name": "wait",
      "parameters": [{
        "name": "timeoutMillis",
        "type": "long"
      }]
    },
    {
      "name": "wait",
      "parameters": [
        {
          "name": "timeoutMillis",
          "type": "long"
        },
        {
          "name": "nanos",
          "type": "int"
        }
      ]
    },
    {
      "name": "getAvailableLocales",
      "return": "java.util.Locale[]"
    },
    {
      "name": "isSupportedLocale",
      "parameters": [{
        "name": "locale",
        "type": "java.util.Locale"
      }],
      "return": "boolean"
    },
    {
      "name": "getDisplayName",
      "parameters": [
        {
          "name": "calendarType",
          "type": "java.lang.String"
        },
        {
          "name": "field",
          "type": "int"
        },
        {
          "name": "value",
          "type": "int"
        },
        {
          "name": "style",
          "type": "int"
        },
        {
          "name": "locale",
          "type": "java.util.Locale"
        }
      ],
      "return": "java.lang.String"
    },
    {
      "name": "getDisplayNames",
      "parameters": [
        {
          "name": "calendarType",
          "type": "java.lang.String"
        },
        {
          "name": "field",
          "type": "int"
        },
        {
          "name": "style",
          "type": "int"
        },
        {
          "name": "locale",
          "type": "java.util.Locale"
        }
      ],
      "return": "java.util.Map"
    }
  ],
  "name": "java.util.spi.CalendarNameProvider",
  "simple-name": "CalendarNameProvider"
}