{
  "constructors": [{"name": "<init>"}],
  "package": "java.util.concurrent.atomic",
  "methods": [
    {
      "name": "getClass",
      "return": "java.lang.Class"
    },
    {
      "name": "hashCode",
      "return": "int"
    },
    {
      "name": "equals",
      "parameters": [{
        "name": "obj",
        "type": "java.lang.Object"
      }],
      "return": "boolean"
    },
    {"name": "notify"},
    {"name": "notifyAll"},
    {"name": "wait"},
    {
      "name": "wait",
      "parameters": [{
        "name": "timeoutMillis",
        "type": "long"
      }]
    },
    {
      "name": "wait",
      "parameters": [
        {
          "name": "timeoutMillis",
          "type": "long"
        },
        {
          "name": "nanos",
          "type": "int"
        }
      ]
    },
    {
      "name": "byteValue",
      "return": "byte"
    },
    {
      "name": "shortValue",
      "return": "short"
    },
    {
      "name": "add",
      "parameters": [{
        "name": "x",
        "type": "double"
      }]
    },
    {
      "name": "sum",
      "return": "double"
    },
    {"name": "reset"},
    {
      "name": "sumThenReset",
      "return": "double"
    },
    {
      "name": "toString",
      "return": "java.lang.String"
    },
    {
      "name": "doubleValue",
      "return": "double"
    },
    {
      "name": "longValue",
      "return": "long"
    },
    {
      "name": "intValue",
      "return": "int"
    },
    {
      "name": "floatValue",
      "return": "float"
    }
  ],
  "name": "java.util.concurrent.atomic.DoubleAdder",
  "simple-name": "DoubleAdder"
}