{"constructors":[{"name":"<init>"}],"package":"java.util.concurrent","methods":[{"name":"getClass","return":"java.lang.Class"},{"name":"hashCode","return":"int"},{"name":"equals","parameters":[{"name":"obj","type":"java.lang.Object"}],"return":"boolean"},{"name":"notify"},{"name":"notifyAll"},{"name":"wait"},{"name":"wait","parameters":[{"name":"timeoutMillis","type":"long"}]},{"name":"wait","parameters":[{"name":"timeoutMillis","type":"long"},{"name":"nanos","type":"int"}]},{"static":true,"name":"supplyAsync","parameters":[{"name":"supplier","type":"java.util.function.Supplier"}],"return":"java.util.concurrent.CompletableFuture"},{"static":true,"name":"supplyAsync","parameters":[{"name":"supplier","type":"java.util.function.Supplier"},{"name":"executor","type":"java.util.concurrent.Executor"}],"return":"java.util.concurrent.CompletableFuture"},{"static":true,"name":"runAsync","parameters":[{"name":"runnable","type":"java.lang.Runnable"}],"return":"java.util.concurrent.CompletableFuture"},{"static":true,"name":"runAsync","parameters":[{"name":"runnable","type":"java.lang.Runnable"},{"name":"executor","type":"java.util.concurrent.Executor"}],"return":"java.util.concurrent.CompletableFuture"},{"static":true,"name":"completedFuture","parameters":[{"name":"value","type":"java.lang.Object"}],"return":"java.util.concurrent.CompletableFuture"},{"name":"isDone","return":"boolean"},{"name":"get","return":"java.lang.Object"},{"name":"get","parameters":[{"name":"timeout","type":"long"},{"name":"unit","type":"java.util.concurrent.TimeUnit"}],"return":"java.lang.Object"},{"name":"join","return":"java.lang.Object"},{"name":"getNow","parameters":[{"name":"valueIfAbsent","type":"java.lang.Object"}],"return":"java.lang.Object"},{"name":"complete","parameters":[{"name":"value","type":"java.lang.Object"}],"return":"boolean"},{"name":"completeExceptionally","parameters":[{"name":"ex","type":"java.lang.Throwable"}],"return":"boolean"},{"name":"thenApply","parameters":[{"name":"fn","type":"java.util.function.Function"}],"return":"java.util.concurrent.CompletableFuture"},{"name":"thenApplyAsync","parameters":[{"name":"fn","type":"java.util.function.Function"}],"return":"java.util.concurrent.CompletableFuture"},{"name":"thenApplyAsync","parameters":[{"name":"fn","type":"java.util.function.Function"},{"name":"executor","type":"java.util.concurrent.Executor"}],"return":"java.util.concurrent.CompletableFuture"},{"name":"thenAccept","parameters":[{"name":"action","type":"java.util.function.Consumer"}],"return":"java.util.concurrent.CompletableFuture"},{"name":"thenAcceptAsync","parameters":[{"name":"action","type":"java.util.function.Consumer"}],"return":"java.util.concurrent.CompletableFuture"},{"name":"thenAcceptAsync","parameters":[{"name":"action","type":"java.util.function.Consumer"},{"name":"executor","type":"java.util.concurrent.Executor"}],"return":"java.util.concurrent.CompletableFuture"},{"name":"thenRun","parameters":[{"name":"action","type":"java.lang.Runnable"}],"return":"java.util.concurrent.CompletableFuture"},{"name":"thenRunAsync","parameters":[{"name":"action","type":"java.lang.Runnable"}],"return":"java.util.concurrent.CompletableFuture"},{"name":"thenRunAsync","parameters":[{"name":"action","type":"java.lang.Runnable"},{"name":"executor","type":"java.util.concurrent.Executor"}],"return":"java.util.concurrent.CompletableFuture"},{"name":"thenCombine","parameters":[{"name":"other","type":"java.util.concurrent.CompletionStage"},{"name":"fn","type":"java.util.function.BiFunction"}],"return":"java.util.concurrent.CompletableFuture"},{"name":"thenCombineAsync","parameters":[{"name":"other","type":"java.util.concurrent.CompletionStage"},{"name":"fn","type":"java.util.function.BiFunction"}],"return":"java.util.concurrent.CompletableFuture"},{"name":"thenCombineAsync","parameters":[{"name":"other","type":"java.util.concurrent.CompletionStage"},{"name":"fn","type":"java.util.function.BiFunction"},{"name":"executor","type":"java.util.concurrent.Executor"}],"return":"java.util.concurrent.CompletableFuture"},{"name":"thenAcceptBoth","parameters":[{"name":"other","type":"java.util.concurrent.CompletionStage"},{"name":"action","type":"java.util.function.BiConsumer"}],"return":"java.util.concurrent.CompletableFuture"},{"name":"thenAcceptBothAsync","parameters":[{"name":"other","type":"java.util.concurrent.CompletionStage"},{"name":"action","type":"java.util.function.BiConsumer"}],"return":"java.util.concurrent.CompletableFuture"},{"name":"thenAcceptBothAsync","parameters":[{"name":"other","type":"java.util.concurrent.CompletionStage"},{"name":"action","type":"java.util.function.BiConsumer"},{"name":"executor","type":"java.util.concurrent.Executor"}],"return":"java.util.concurrent.CompletableFuture"},{"name":"runAfterBoth","parameters":[{"name":"other","type":"java.util.concurrent.CompletionStage"},{"name":"action","type":"java.lang.Runnable"}],"return":"java.util.concurrent.CompletableFuture"},{"name":"runAfterBothAsync","parameters":[{"name":"other","type":"java.util.concurrent.CompletionStage"},{"name":"action","type":"java.lang.Runnable"}],"return":"java.util.concurrent.CompletableFuture"},{"name":"runAfterBothAsync","parameters":[{"name":"other","type":"java.util.concurrent.CompletionStage"},{"name":"action","type":"java.lang.Runnable"},{"name":"executor","type":"java.util.concurrent.Executor"}],"return":"java.util.concurrent.CompletableFuture"},{"name":"applyToEither","parameters":[{"name":"other","type":"java.util.concurrent.CompletionStage"},{"name":"fn","type":"java.util.function.Function"}],"return":"java.util.concurrent.CompletableFuture"},{"name":"applyToEitherAsync","parameters":[{"name":"other","type":"java.util.concurrent.CompletionStage"},{"name":"fn","type":"java.util.function.Function"}],"return":"java.util.concurrent.CompletableFuture"},{"name":"applyToEitherAsync","parameters":[{"name":"other","type":"java.util.concurrent.CompletionStage"},{"name":"fn","type":"java.util.function.Function"},{"name":"executor","type":"java.util.concurrent.Executor"}],"return":"java.util.concurrent.CompletableFuture"},{"name":"acceptEither","parameters":[{"name":"other","type":"java.util.concurrent.CompletionStage"},{"name":"action","type":"java.util.function.Consumer"}],"return":"java.util.concurrent.CompletableFuture"},{"name":"acceptEitherAsync","parameters":[{"name":"other","type":"java.util.concurrent.CompletionStage"},{"name":"action","type":"java.util.function.Consumer"}],"return":"java.util.concurrent.CompletableFuture"},{"name":"acceptEitherAsync","parameters":[{"name":"other","type":"java.util.concurrent.CompletionStage"},{"name":"action","type":"java.util.function.Consumer"},{"name":"executor","type":"java.util.concurrent.Executor"}],"return":"java.util.concurrent.CompletableFuture"},{"name":"runAfterEither","parameters":[{"name":"other","type":"java.util.concurrent.CompletionStage"},{"name":"action","type":"java.lang.Runnable"}],"return":"java.util.concurrent.CompletableFuture"},{"name":"runAfterEitherAsync","parameters":[{"name":"other","type":"java.util.concurrent.CompletionStage"},{"name":"action","type":"java.lang.Runnable"}],"return":"java.util.concurrent.CompletableFuture"},{"name":"runAfterEitherAsync","parameters":[{"name":"other","type":"java.util.concurrent.CompletionStage"},{"name":"action","type":"java.lang.Runnable"},{"name":"executor","type":"java.util.concurrent.Executor"}],"return":"java.util.concurrent.CompletableFuture"},{"name":"thenCompose","parameters":[{"name":"fn","type":"java.util.function.Function"}],"return":"java.util.concurrent.CompletableFuture"},{"name":"thenComposeAsync","parameters":[{"name":"fn","type":"java.util.function.Function"}],"return":"java.util.concurrent.CompletableFuture"},{"name":"thenComposeAsync","parameters":[{"name":"fn","type":"java.util.function.Function"},{"name":"executor","type":"java.util.concurrent.Executor"}],"return":"java.util.concurrent.CompletableFuture"},{"name":"whenComplete","parameters":[{"name":"action","type":"java.util.function.BiConsumer"}],"return":"java.util.concurrent.CompletableFuture"},{"name":"whenCompleteAsync","parameters":[{"name":"action","type":"java.util.function.BiConsumer"}],"return":"java.util.concurrent.CompletableFuture"},{"name":"whenCompleteAsync","parameters":[{"name":"action","type":"java.util.function.BiConsumer"},{"name":"executor","type":"java.util.concurrent.Executor"}],"return":"java.util.concurrent.CompletableFuture"},{"name":"handle","parameters":[{"name":"fn","type":"java.util.function.BiFunction"}],"return":"java.util.concurrent.CompletableFuture"},{"name":"handleAsync","parameters":[{"name":"fn","type":"java.util.function.BiFunction"}],"return":"java.util.concurrent.CompletableFuture"},{"name":"handleAsync","parameters":[{"name":"fn","type":"java.util.function.BiFunction"},{"name":"executor","type":"java.util.concurrent.Executor"}],"return":"java.util.concurrent.CompletableFuture"},{"name":"toCompletableFuture","return":"java.util.concurrent.CompletableFuture"},{"name":"exceptionally","parameters":[{"name":"fn","type":"java.util.function.Function"}],"return":"java.util.concurrent.CompletableFuture"},{"name":"exceptionallyAsync","parameters":[{"name":"fn","type":"java.util.function.Function"}],"return":"java.util.concurrent.CompletableFuture"},{"name":"exceptionallyAsync","parameters":[{"name":"fn","type":"java.util.function.Function"},{"name":"executor","type":"java.util.concurrent.Executor"}],"return":"java.util.concurrent.CompletableFuture"},{"name":"exceptionallyCompose","parameters":[{"name":"fn","type":"java.util.function.Function"}],"return":"java.util.concurrent.CompletableFuture"},{"name":"exceptionallyComposeAsync","parameters":[{"name":"fn","type":"java.util.function.Function"}],"return":"java.util.concurrent.CompletableFuture"},{"name":"exceptionallyComposeAsync","parameters":[{"name":"fn","type":"java.util.function.Function"},{"name":"executor","type":"java.util.concurrent.Executor"}],"return":"java.util.concurrent.CompletableFuture"},{"static":true,"name":"allOf","parameters":[{"name":"cfs","type":"java.util.concurrent.CompletableFuture[]"}],"return":"java.util.concurrent.CompletableFuture"},{"static":true,"name":"anyOf","parameters":[{"name":"cfs","type":"java.util.concurrent.CompletableFuture[]"}],"return":"java.util.concurrent.CompletableFuture"},{"name":"cancel","parameters":[{"name":"mayInterruptIfRunning","type":"boolean"}],"return":"boolean"},{"name":"isCancelled","return":"boolean"},{"name":"isCompletedExceptionally","return":"boolean"},{"name":"obtrudeValue","parameters":[{"name":"value","type":"java.lang.Object"}]},{"name":"obtrudeException","parameters":[{"name":"ex","type":"java.lang.Throwable"}]},{"name":"getNumberOfDependents","return":"int"},{"name":"toString","return":"java.lang.String"},{"name":"newIncompleteFuture","return":"java.util.concurrent.CompletableFuture"},{"name":"defaultExecutor","return":"java.util.concurrent.Executor"},{"name":"copy","return":"java.util.concurrent.CompletableFuture"},{"name":"minimalCompletionStage","return":"java.util.concurrent.CompletionStage"},{"name":"completeAsync","parameters":[{"name":"supplier","type":"java.util.function.Supplier"},{"name":"executor","type":"java.util.concurrent.Executor"}],"return":"java.util.concurrent.CompletableFuture"},{"name":"completeAsync","parameters":[{"name":"supplier","type":"java.util.function.Supplier"}],"return":"java.util.concurrent.CompletableFuture"},{"name":"orTimeout","parameters":[{"name":"timeout","type":"long"},{"name":"unit","type":"java.util.concurrent.TimeUnit"}],"return":"java.util.concurrent.CompletableFuture"},{"name":"completeOnTimeout","parameters":[{"name":"value","type":"java.lang.Object"},{"name":"timeout","type":"long"},{"name":"unit","type":"java.util.concurrent.TimeUnit"}],"return":"java.util.concurrent.CompletableFuture"},{"static":true,"name":"delayedExecutor","parameters":[{"name":"delay","type":"long"},{"name":"unit","type":"java.util.concurrent.TimeUnit"},{"name":"executor","type":"java.util.concurrent.Executor"}],"return":"java.util.concurrent.Executor"},{"static":true,"name":"delayedExecutor","parameters":[{"name":"delay","type":"long"},{"name":"unit","type":"java.util.concurrent.TimeUnit"}],"return":"java.util.concurrent.Executor"},{"static":true,"name":"completedStage","parameters":[{"name":"value","type":"java.lang.Object"}],"return":"java.util.concurrent.CompletionStage"},{"static":true,"name":"failedFuture","parameters":[{"name":"ex","type":"java.lang.Throwable"}],"return":"java.util.concurrent.CompletableFuture"},{"static":true,"name":"failedStage","parameters":[{"name":"ex","type":"java.lang.Throwable"}],"return":"java.util.concurrent.CompletionStage"}],"name":"java.util.concurrent.CompletableFuture","simple-name":"CompletableFuture"}